<?xml version="1.0" encoding="UTF-8"?>
<!--This is a Reload version 2.5.2 SCORM 1.2 Content Package document-->
<!--Spawned from the Reload Content Package Generator - http://www.reload.ac.uk-->
<manifest xmlns="http://www.imsproject.org/xsd/imscp_rootv1p1p2" xmlns:imsmd="http://www.imsglobal.org/xsd/imsmd_rootv1p2p1" xmlns:xsi="http://www.w3.org/2001/XMLSchema-instance" xmlns:adlcp="http://www.adlnet.org/xsd/adlcp_rootv1p2" identifier="Introducción a la Gestión Empresarial" xsi:schemaLocation="http://www.imsproject.org/xsd/imscp_rootv1p1p2 imscp_rootv1p1p2.xsd http://www.imsglobal.org/xsd/imsmd_rootv1p2p1 imsmd_rootv1p2p1.xsd http://www.adlnet.org/xsd/adlcp_rootv1p2 adlcp_rootv1p2.xsd" version="1.2">
  <metadata>
    <schema>ADL SCORM</schema>
    <schemaversion>1.2</schemaversion>
    <adlcp:location />
  </metadata>
  <organizations default="ORG-32723D0B-6D20-DEF6-453F-DDFD462820FA">
    <organization identifier="ORG-32723D0B-6D20-DEF6-453F-DDFD462820FA" structure="hierarchical">
      <title>Curso de Introducción a la Gestión Empresarial</title>
      <item identifier="ITEM-69EF932C-DB87-7CC4-66D5-668CEE23231D" identifierref="RES-C745BA11-0609-7D72-2A39-87CF47FA7437" isvisible="true">
        <title>Tema 0: Introducción al Plan de Empresa</title>
      </item>
      <item identifier="ITEM-89F52720-9EB6-A78D-31FB-F74881BCA5A3" identifierref="RES-57BF6807-C441-6C3B-A251-B92640BA8229" isvisible="true">
        <title>Tema 1: Breve Historia de la Idea</title>
      </item>
      <item identifier="ITEM-E57579CD-B84D-0A67-0F97-DACB71A64155" identifierref="RES-B6C8B7D5-73C7-D3EE-1ABD-C8ABC18F10BE" isvisible="true">
        <title>Tema 2: Plan de Marketing</title>
      </item>
      <item identifier="ITEM-C3EAA436-E01A-29B0-A08C-A10CCE9857B2" identifierref="RES-30E9F95D-95D6-09CE-2989-2CDD41918360" isvisible="true">
        <title>Tema 3: Estudio del Mercado</title>
      </item>
      <item identifier="ITEM-0EA6EE90-3224-E1D4-27EA-379048AF2C07" identifierref="RES-0C7B5478-90A7-91A9-F512-C4AD3EB23D98" isvisible="true">
        <title>Tema 4: Plan Comercial</title>
      </item>
      <item identifier="ITEM-B5F21F21-ED44-10B6-CC11-47C096902B39" identifierref="RES-251DD125-84F4-946C-0032-2774CB03AF5F" isvisible="true">
        <title>Tema 5: Plan de Recursos Humanos</title>
      </item>
      <item identifier="ITEM-74CE7941-D49B-57DF-0947-B8388FCD3AAC" identifierref="RES-08AF8405-A858-6F79-296E-C1E0B643F1FA" isvisible="true">
        <title>Tema 6: Formas Elegidas</title>
      </item>
      <item identifier="ITEM-201EDF1F-6627-9AE8-65B6-A2DF758BC27D" identifierref="RES-E4CA6599-A44E-2E20-188B-78D108BBC81E" isvisible="true">
        <title>Tema 7: Trámites de Constitución</title>
      </item>
      <item identifier="ITEM-F98AB4E5-8000-C420-E5FE-FFCBAA5D78F1" identifierref="RES-53C41895-D0FD-A6A8-811D-9907CF1BBA7F" isvisible="true">
        <title>Tema 8: Formas Jurídicas Caracterísitcas</title>
      </item>
      <item identifier="ITEM-EC3A2AA9-33E8-EB4D-E58E-E5BD84FDC50C" identifierref="RES-82241400-4A84-10B8-386E-112DA64D9EBA" isvisible="true">
        <title>Tema 9: Plan de Inversión</title>
      </item>
      <item identifier="ITEM-AF47604E-AFC8-9461-AF8E-4E9E51DCDD9D" identifierref="RES-D90B2733-D854-2CA8-5F31-82F1C57FD869" isvisible="true">
        <title>Tema 10: Plan de Financiación</title>
      </item>
      <item identifier="ITEM-C4005EEE-9F05-19DC-63F7-316D6F962F16" identifierref="RES-58B73B93-783B-6BE9-4CF8-0C491EE26DB6" isvisible="true">
        <title>Tema 11: Balance de Situación</title>
      </item>
      <item identifier="ITEM-DA61AAB4-3AC0-72DF-3269-2627F71DA610" identifierref="RES-6E922ED9-3187-A146-F0D6-8A40C6140E8A" isvisible="true">
        <title>Tema 12: Cuenta de Pérdidas y Ganancias</title>
      </item>
      <item identifier="ITEM-0280F286-55A9-23C4-E100-62D06DB3300F" identifierref="RES-355AC736-421E-B154-AD9E-AD9C0C56DFED" isvisible="true">
        <title>Tema 13: Obligaciones Fiscales</title>
      </item>
      <item identifier="ITEM-0E20B180-13DA-0FC6-BD1E-FCA2B3C72D7B" identifierref="RES-4D2A1978-05E8-97B8-1B10-29E1755FD241" isvisible="true">
        <title>Tema 14: Cuadro de Tesorería</title>
      </item>
      <item identifier="ITEM-B75BE34B-B6B7-6B9C-8761-B90C2EC4E9D0" identifierref="RES-05263F45-EB55-0038-649B-D05AD4F0880B" isvisible="true">
        <title>Tema 15: Ratios</title>
      </item>
      <item identifier="ITEM-BE99AD02-6DDF-FAC3-3AC7-726756001395" identifierref="RES-96F91142-AE72-61E3-7D11-75E5034FD9A1" isvisible="true">
        <title>Tema 16: Primer Documento de Trabajo</title>
      </item>
      <item identifier="ITEM-837A145E-4AD7-6B35-53CE-964E75A864EA" identifierref="RES-4B36A8D2-CC2F-5B16-6370-B75468206EBE" isvisible="true">
        <title>Tema 17: Segundo Documento de Trabajo</title>
      </item>
    </organization>
  </organizations>
  <resources>
    <resource href="tema0/0.html" identifier="RES-C745BA11-0609-7D72-2A39-87CF47FA7437" adlcp:scormtype="sco" type="webcontent">
      <file href="tema0/0.html" />
      <file href="tema0/0.swf" />
      <dependency identifierref="R_shared" />
    </resource>
    <resource href="tema1/1.html" identifier="RES-57BF6807-C441-6C3B-A251-B92640BA8229" adlcp:scormtype="sco" type="webcontent">
      <file href="tema1/1.html" />
      <file href="tema1/1.swf" />
      <file href="tema1/cp1.doc" />
      <dependency identifierref="R_shared" />
      <dependency identifierref="casos1" />
    </resource>
    <resource identifier="casos1" adlcp:scormtype="asset" type="webcontent">
      <file href="tema1/1_1_launcher.html" />
      <file href="tema1/1_1_viewlet_swf.html" />
      <file href="tema1/1_4.swf" />
      <file href="tema1/1_1.swf" />
      <file href="tema1/1_2.swf" />
      <file href="tema1/1_2_launcher.html" />
      <file href="tema1/1_2_viewlet_swf.html" />
      <file href="tema1/1_3.swf" />
      <file href="tema1/1_3_launcher.html" />
      <file href="tema1/1_3_viewlet_swf.html" />
      <file href="tema1/1_4_launcher.html" />
      <file href="tema1/1_4_viewlet_swf.html" />
      <file href="tema1/1_5.swf" />
      <file href="tema1/1_5_launcher.html" />
      <file href="tema1/1_5_viewlet_swf.html" />
      <file href="tema1/1_6.swf" />
      <file href="tema1/1_6_launcher.html" />
      <file href="tema1/1_6_viewlet_swf.html" />
      <file href="tema1/1_7.swf" />
      <file href="tema1/1_7_launcher.html" />
      <file href="tema1/1_7_viewlet_swf.html" />
    </resource>
    <resource href="tema2/2.html" identifier="RES-B6C8B7D5-73C7-D3EE-1ABD-C8ABC18F10BE" adlcp:scormtype="sco" type="webcontent">
      <file href="tema2/2.html" />
      <file href="tema2/2.swf" />
      <file href="tema2/2_1.swf" />
      <file href="tema2/2_1_launcher.html" />
      <file href="tema2/2_1_viewlet_swf.html" />
      <file href="tema2/2_2.swf" />
      <file href="tema2/2_2_launcher.html" />
      <file href="tema2/2_2_viewlet_swf.html" />
      <file href="tema2/2_4.swf" />
      <file href="tema2/2_4_launcher.html" />
      <file href="tema2/2_4_viewlet_swf.html" />
      <file href="tema2/2_5.swf" />
      <file href="tema2/2_5_launcher.html" />
      <file href="tema2/2_5_viewlet_swf.html" />
      <file href="tema2/cp2.doc" />
      <dependency identifierref="R_shared" />
    </resource>
    <resource href="tema3/3.html" identifier="RES-30E9F95D-95D6-09CE-2989-2CDD41918360" adlcp:scormtype="sco" type="webcontent">
      <file href="tema3/3.html" />
      <file href="tema3/3.swf" />
      <file href="tema3/3_1.swf" />
      <file href="tema3/3_1_launcher.html" />
      <file href="tema3/3_1_viewlet_swf.html" />
      <file href="tema3/3_2_1.swf" />
      <file href="tema3/3_2_1_launcher.html" />
      <file href="tema3/3_2_1_viewlet_swf.html" />
      <file href="tema3/3_2_2_1.swf" />
      <file href="tema3/3_2_2_1_launcher.html" />
      <file href="tema3/3_2_2_1_viewlet_swf.html" />
      <file href="tema3/3_3_1.swf" />
      <file href="tema3/3_3_1_launcher.html" />
      <file href="tema3/3_3_1_viewlet_swf.html" />
      <file href="tema3/3_3_2.swf" />
      <file href="tema3/3_3_2_launcher.html" />
      <file href="tema3/3_3_2_viewlet_swf.html" />
      <file href="tema3/3_4.swf" />
      <file href="tema3/3_4_1.swf" />
      <file href="tema3/3_4_1_launcher.html" />
      <file href="tema3/3_4_1_viewlet_swf.html" />
      <file href="tema3/3_4_2.swf" />
      <file href="tema3/3_4_2_launcher.html" />
      <file href="tema3/3_4_2_viewlet_swf.html" />
      <file href="tema3/3_4_launcher.html" />
      <file href="tema3/3_4_viewlet_swf.html" />
      <file href="tema3/cp3.doc" />
      <dependency identifierref="R_shared" />
    </resource>
    <resource href="tema4/4.html" identifier="RES-0C7B5478-90A7-91A9-F512-C4AD3EB23D98" adlcp:scormtype="sco" type="webcontent">
      <file href="tema4/4.html" />
      <file href="tema4/4.swf" />
      <file href="tema4/4_1.swf" />
      <file href="tema4/4_1_launcher.html" />
      <file href="tema4/4_1_viewlet_swf.html" />
      <file href="tema4/4_2.swf" />
      <file href="tema4/4_2_launcher.html" />
      <file href="tema4/4_2_viewlet_swf.html" />
      <file href="tema4/4_3.swf" />
      <file href="tema4/4_3_launcher.html" />
      <file href="tema4/4_3_viewlet_swf.html" />
      <file href="tema4/4_4.swf" />
      <file href="tema4/4_4_launcher.html" />
      <file href="tema4/4_4_viewlet_swf.html" />
      <file href="tema4/4_5.swf" />
      <file href="tema4/4_5_launcher.html" />
      <file href="tema4/4_5_viewlet_swf.html" />
      <file href="tema4/4_6.swf" />
      <file href="tema4/4_6_launcher.html" />
      <file href="tema4/4_6_viewlet_swf.html" />
      <file href="tema4/5_1.swf" />
      <file href="tema4/5_1_launcher.html" />
      <file href="tema4/5_1_viewlet_swf.html" />
      <file href="tema4/5_2_1.swf" />
      <file href="tema4/5_2_1_launcher.html" />
      <file href="tema4/5_2_1_viewlet_swf.html" />
      <file href="tema4/5_2_2_1.swf" />
      <file href="tema4/5_2_2_1_launcher.html" />
      <file href="tema4/5_2_2_1_viewlet_swf.html" />
      <file href="tema4/5_2_2_2.swf" />
      <file href="tema4/5_2_2_2_launcher.html" />
      <file href="tema4/5_2_2_2_viewlet_swf.html" />
      <file href="tema4/5_3.swf" />
      <file href="tema4/5_3_launcher.html" />
      <file href="tema4/5_3_viewlet_swf.html" />
      <file href="tema4/5_4.swf" />
      <file href="tema4/5_4_launcher.html" />
      <file href="tema4/5_4_viewlet_swf.html" />
      <file href="tema4/5_5.swf" />
      <file href="tema4/5_5_launcher.html" />
      <file href="tema4/5_5_viewlet_swf.html" />
      <file href="tema4/5_7_1.swf" />
      <file href="tema4/5_7_1_launcher.html" />
      <file href="tema4/5_7_1_viewlet_swf.html" />
      <file href="tema4/5_7_2.swf" />
      <file href="tema4/5_7_2_launcher.html" />
      <file href="tema4/5_7_2_viewlet_swf.html" />
      <file href="tema4/comprasventas.doc" />
      <file href="tema4/comprasventas_vacio.xls" />
      <file href="tema4/compras_y_ventas2.swf" />
      <file href="tema4/compras_y_ventas2_launcher.html" />
      <file href="tema4/compras_y_ventas2_viewlet_swf.html" />
      <file href="tema4/cp4.doc" />
      <dependency identifierref="R_shared" />
    </resource>
    <resource href="tema5/5.html" identifier="RES-251DD125-84F4-946C-0032-2774CB03AF5F" adlcp:scormtype="sco" type="webcontent">
      <file href="tema5/5.html" />
      <file href="tema5/5.swf" />
      <file href="tema5/7_1.swf" />
      <file href="tema5/7_1_launcher.html" />
      <file href="tema5/7_1_viewlet_swf.html" />
      <file href="tema5/7_2.swf" />
      <file href="tema5/7_2_launcher.html" />
      <file href="tema5/7_2_viewlet_swf.html" />
      <file href="tema5/7_3.swf" />
      <file href="tema5/7_3_launcher.html" />
      <file href="tema5/7_3_viewlet_swf.html" />
      <file href="tema5/7_4.swf" />
      <file href="tema5/7_4_launcher.html" />
      <file href="tema5/7_4_viewlet_swf.html" />
      <file href="tema5/7_7.swf" />
      <file href="tema5/7_7_launcher.html" />
      <file href="tema5/7_7_viewlet_swf.html" />
      <file href="tema5/cp5.doc" />
      <file href="tema5/personal.doc" />
      <file href="tema5/personal.swf" />
      <file href="tema5/personal_launcher.html" />
      <file href="tema5/personal_vacio.xls" />
      <file href="tema5/personal_viewlet_swf.html" />
      <dependency identifierref="R_shared" />
    </resource>
    <resource href="tema6/6.html" identifier="RES-08AF8405-A858-6F79-296E-C1E0B643F1FA" adlcp:scormtype="sco" type="webcontent">
      <file href="tema6/6.html" />
      <file href="tema6/6.swf" />
      <file href="tema6/formasjuridicas.html" />
      <file href="tema6/formasjuridicas.jpg" />
      <file href="tema6/Thumbs.db" />
      <dependency identifierref="R_shared" />
    </resource>
    <resource href="tema7/7.html" identifier="RES-E4CA6599-A44E-2E20-188B-78D108BBC81E" adlcp:scormtype="sco" type="webcontent">
      <file href="tema7/7.html" />
      <file href="tema7/7.swf" />
      <file href="tema7/constitucioncivil.doc" />
      <file href="tema7/constitucionEmpresarioIndividual.doc" />
      <file href="tema7/constitucionsasl.doc" />
      <dependency identifierref="R_shared" />
    </resource>
    <resource href="tema8/8.html" identifier="RES-53C41895-D0FD-A6A8-811D-9907CF1BBA7F" adlcp:scormtype="sco" type="webcontent">
      <file href="tema8/8.html" />
      <file href="tema8/8.swf" />
      <file href="tema8/fjcombienes.gif" />
      <file href="tema8/fjempind.gif" />
      <file href="tema8/fjsa.gif" />
      <file href="tema8/fjsc.gif" />
      <file href="tema8/fjsl.gif" />
      <file href="tema8/fjslab.gif" />
      <file href="tema8/fjslne.gif" />
      <file href="tema8/formasjuridicas.jpg" />
      <file href="tema8/Thumbs.db" />
      <dependency identifierref="R_shared" />
    </resource>
    <resource href="tema9/9.html" identifier="RES-82241400-4A84-10B8-386E-112DA64D9EBA" adlcp:scormtype="sco" type="webcontent">
      <file href="tema9/9.html" />
      <file href="tema9/9.swf" />
      <file href="tema9/datosinversion1.xls" />
      <file href="tema9/datosinversion2.xls" />
      <file href="tema9/datosinversion3.xls" />
      <file href="tema9/planinversion_vacio.xls" />
      <file href="tema9/plan_de_inversion2.swf" />
      <file href="tema9/plan_de_inversion2_launcher.html" />
      <file href="tema9/plan_de_inversion2_viewlet_swf.html" />
      <dependency identifierref="R_shared" />
    </resource>
    <resource href="tema10/10.html" identifier="RES-D90B2733-D854-2CA8-5F31-82F1C57FD869" adlcp:scormtype="sco" type="webcontent">
      <file href="tema10/10.html" />
      <file href="tema10/10.swf" />
      <file href="tema10/amortizaciones.swf" />
      <file href="tema10/amortizaciones_launcher.html" />
      <file href="tema10/amortizaciones_vacio.xls" />
      <file href="tema10/amortizaciones_viewlet_swf.html" />
      <file href="tema10/balanceinicial.xls" />
      <file href="tema10/planfinanciero_vacio.xls" />
      <file href="tema10/plan_de_financiacion2.swf" />
      <file href="tema10/plan_de_financiacion2_launcher.html" />
      <file href="tema10/plan_de_financiacion2_viewlet_swf.html" />
      <dependency identifierref="R_shared" />
    </resource>
    <resource href="tema11/11.html" identifier="RES-58B73B93-783B-6BE9-4CF8-0C491EE26DB6" adlcp:scormtype="sco" type="webcontent">
      <file href="tema11/11.html" />
      <file href="tema11/11.swf" />
      <file href="tema11/balanceinicial_vacio.xls" />
      <file href="tema11/balance_de_situacion.swf" />
      <file href="tema11/balance_de_situacion_launcher.html" />
      <file href="tema11/balance_de_situacion_viewlet_swf.html" />
      <dependency identifierref="R_shared" />
    </resource>
    <resource href="tema12/12.html" identifier="RES-6E922ED9-3187-A146-F0D6-8A40C6140E8A" adlcp:scormtype="sco" type="webcontent">
      <file href="tema12/12.html" />
      <file href="tema12/12.swf" />
      <file href="tema12/cuentaperdidasganancias_vacio.xls" />
      <file href="tema12/Cuenta_Perdidas_Ganancias.swf" />
      <file href="tema12/Cuenta_Perdidas_Ganancias_launcher.html" />
      <file href="tema12/Cuenta_Perdidas_Ganancias_viewlet_swf.html" />
      <file href="tema12/serviciosexteriores.doc" />
      <dependency identifierref="R_shared" />
    </resource>
    <resource href="tema13/13.html" identifier="RES-355AC736-421E-B154-AD9E-AD9C0C56DFED" adlcp:scormtype="sco" type="webcontent">
      <file href="tema13/13.html" />
      <file href="tema13/13.swf" />
      <file href="tema13/ivas.swf" />
      <file href="tema13/iva_vacio.xls" />
      <file href="tema13/ivas_launcher.html" />
      <file href="tema13/ivas_viewlet_swf.html" />
      <dependency identifierref="R_shared" />
    </resource>
    <resource href="tema14/14.html" identifier="RES-4D2A1978-05E8-97B8-1B10-29E1755FD241" adlcp:scormtype="sco" type="webcontent">
      <file href="tema14/14.html" />
      <file href="tema14/14.swf" />
      <file href="tema14/cuadrotesoreria_vacio.xls" />
      <file href="tema14/tesoreria2.swf" />
      <file href="tema14/tesoreria2_launcher.html" />
      <file href="tema14/tesoreria2_viewlet_swf.html" />
      <dependency identifierref="R_shared" />
    </resource>
    <resource href="tema15/15.html" identifier="RES-05263F45-EB55-0038-649B-D05AD4F0880B" adlcp:scormtype="sco" type="webcontent">
      <file href="tema15/15.html" />
      <file href="tema15/15.swf" />
      <file href="tema15/ratios_vacio.xls" />
      <file href="tema15/ratios.xls" />
      <dependency identifierref="R_shared" />
    </resource>
    <resource href="tema16/16.html" identifier="RES-96F91142-AE72-61E3-7D11-75E5034FD9A1" adlcp:scormtype="sco" type="webcontent">
      <file href="tema16/16.html" />
      <file href="tema16/16.swf" />
      <file href="tema16/PrimerDocumentodeTrabajo.doc" />
      <dependency identifierref="R_shared" />
    </resource>
    <resource href="tema17/17.html" identifier="RES-4B36A8D2-CC2F-5B16-6370-B75468206EBE" adlcp:scormtype="sco" type="webcontent">
      <file href="tema17/17.html" />
      <file href="tema17/17.swf" />
      <file href="tema17/amortizaciones_vacio.xls" />
      <file href="tema17/SegundoDocumentodeTrabajo.xls" />
      <file href="tema17/tuplandeempresa.xls" />
      <dependency identifierref="R_shared" />
    </resource>
    <resource identifier="R_shared" adlcp:scormtype="asset" type="webcontent">
      <file href="shared/js/apiwrapper.js" />
      <file href="shared/js/Thumbs.db" />
      <file href="shared/ayuda.pdf" />
    </resource>
  </resources>
</manifest>

